vnpy_bybit/__init__.py
vnpy_bybit/bybit_gateway.py
vnpy_bybit-2024.9.18.dist-info/LICENSE
vnpy_bybit-2024.9.18.dist-info/METADATA
vnpy_bybit-2024.9.18.dist-info/WHEEL
vnpy_bybit-2024.9.18.dist-info/top_level.txt
vnpy_bybit-2024.9.18.dist-info/RECORD
