Metadata-Version: 2.1
Name: vnpy-bybit
Version: 2024.9.18
Summary: Bybit trading gateway for VeighNa Evo.
Home-page: https://www.github.com/veighna-global
Author: VeighNa Global
Author-email: veighna@hotmail.com
Keywords: quant,quantitative,investment,trading,algotrading,bybit,btc,crypto
Classifier: Development Status :: 5 - Production/Stable
Classifier: Operating System :: Microsoft :: Windows
Classifier: Operating System :: POSIX :: Linux
Classifier: Operating System :: MacOS
Classifier: Programming Language :: Python :: 3
Classifier: Programming Language :: Python :: 3.10
Classifier: Programming Language :: Python :: 3.11
Classifier: Programming Language :: Python :: 3.12
Classifier: Topic :: Office/Business :: Financial :: Investment
Classifier: Programming Language :: Python :: Implementation :: CPython
Classifier: License :: OSI Approved :: MIT License
Classifier: Natural Language :: English
License-File: LICENSE
Requires-Dist: vnpy-evo
